behaviorcloud/__init__.py
behaviorcloud/analyzer/__init__.py
behaviorcloud/analyzer/analyzer.py
behaviorcloud/analyzer/api.py
behaviorcloud/analyzer/coordinator.py
behaviorcloud/analyzer/data.py
behaviorcloud/analyzer/globals.py
bc_analyzer-0.2.3.dist-info/LICENSE.txt
bc_analyzer-0.2.3.dist-info/WHEEL
bc_analyzer-0.2.3.dist-info/METADATA
bc_analyzer-0.2.3.dist-info/RECORD
