Metadata-Version: 2.1
Name: bc-analyzer
Version: 0.2.3
Summary: A package to create a BehaviorCloud compatible data analyzer.
Home-page: https://github.com/behaviorcloud/bc-analyzer-py
License: MIT
Keywords: behaviorcloud,behavior,cloud,analyzer,analyze,analysis,data,daemon,api
Author: Christian Lent
Author-email: christian@behaviorcloud.com
Requires-Python: >=3.6,<4.0
Classifier: Development Status :: 3 - Alpha
Classifier: Intended Audience :: Developers
Classifier: License :: OSI Approved :: MIT License
Classifier: Programming Language :: Python :: 3
Classifier: Programming Language :: Python :: 3.6
Classifier: Programming Language :: Python :: 3.7
Classifier: Programming Language :: Python :: 3.8
Classifier: Programming Language :: Python :: 3.9
Classifier: Topic :: Software Development :: Build Tools
Requires-Dist: deepdiff (>=4.3.2,<5.0.0)
Requires-Dist: python-dateutil (>=2.8.1,<3.0.0)
Requires-Dist: requests (==2.23.0)
Requires-Dist: sentry-sdk (>=0.14.4,<0.15.0)
Project-URL: Repository, https://github.com/behaviorcloud/bc-analyzer-py
